ttspersian/__init__.py
ttspersian/persiantts.py
ttspersian-0.1.0.dist-info/METADATA
ttspersian-0.1.0.dist-info/WHEEL
ttspersian-0.1.0.dist-info/top_level.txt
ttspersian-0.1.0.dist-info/RECORD
