Metadata-Version: 2.2
Name: ttspersian
Version: 0.1.0
Summary: A Python library for Persian text-to-speech using Microsoft Azure service.
Author-email: Ali Jahani <satreyek@gmail.com>
Project-URL: Homepage, https://github.com/alipyth
Project-URL: website, https://jahaniwww.com
Classifier: Programming Language :: Python :: 3
Classifier: License :: OSI Approved :: MIT License
Classifier: Operating System :: OS Independent
Requires-Python: >=3.7
Requires-Dist: websockets
Requires-Dist: asyncio
Requires-Dist: librosa
Requires-Dist: soundfile
Requires-Dist: noisereduce
